Workbook

Sheet Параметры плана
A1: Параметры плана: ECCO Kids — медиаплан Яндекс Директ
A2: Бюджет и AOV — цифры для формул; ниже — условия, по которым собран сплит кампаний и воронка до покупки.
A4: Данные для расчёта
A5: Источник | B5: Параметр | C5: Значение | D5: Ед.
A6: из исходных данных | B6: Месячный бюджет без НДС | C6: 1000000 | D6: ₽
A7: информация с сайта | B7: Средний чек (AOV) | C7: 4250 | D7: ₽
A8: из исходных данных | B8: Горизонт планирования | C8: 12 | D8: мес
A10: Условия расчёта
A11: Источник | B11: Условие | C11: Значение
A12: из исходных данных | B12: Целевое действие | C12: Покупка на сайте (Метрика)
A13: из исходных данных | B13: KPI эффективности | C13: ДРР = расход без НДС / выручка
A14: из исходных данных | B14: Коридор ДРР | C14: 15–25%
A15: принимаем значение | B15: Распределение бюджета по месяцам | C15: Сезонные веса (таблица ниже): пики сен/окт и янв; лето ниже базы; год = 12 млн ₽ без НДС
A16: принимаем значение | B16: Места показа | C16: Поиск и РСЯ — отдельные ЕПК, не смешиваем
A17: принимаем значение | B17: Воронка | C17: Показы → клики → покупки → выручка
A19: Сезонность по месяцам
A20: Месяц | B20: Вес | C20: Бюджет канала, ₽
A21: Сен 2026 | B21: 1.15 | C21: =ROUND($C$6*B21,0)
A22: Окт 2026 | B22: 1.1 | C22: =ROUND($C$6*B22,0)
A23: Ноя 2026 | B23: 1.05 | C23: =ROUND($C$6*B23,0)
A24: Дек 2026 | B24: 1.05 | C24: =ROUND($C$6*B24,0)
A25: Янв 2027 | B25: 1.15 | C25: =ROUND($C$6*B25,0)
A26: Фев 2027 | B26: 1.05 | C26: =ROUND($C$6*B26,0)
A27: Мар 2027 | B27: 1 | C27: =ROUND($C$6*B27,0)
A28: Апр 2027 | B28: 0.95 | C28: =ROUND($C$6*B28,0)
A29: Май 2027 | B29: 0.9 | C29: =ROUND($C$6*B29,0)
A30: Июн 2027 | B30: 0.85 | C30: =ROUND($C$6*B30,0)
A31: Июл 2027 | B31: 0.8 | C31: =ROUND($C$6*B31,0)
A32: Авг 2027 | B32: 0.95 | C32: =ROUND($C$6*B32,0)
A33: Итого | B33: =SUM(B21:B32) | C33: =SUM(C21:C32)
A35: Комментарий к расчёту
A36: На листе разделены цифры, которые подставляются в формулы, и правила, по которым собран медиаплан. 1 000 000 ₽/мес без НДС — опорный месяц (вес 1,0); на сетке года к базовому расходу кампании умножаются сезонные веса из таблицы ниже — сумма весов 12, годовой расход канала 12 000 000 ₽. AOV 4 250 ₽ взяли с витрины kids/boys как рабочую оценку среднего чека: от него считается выручка и весь ДРР. Цель воронки — «Покупка на сайте»; KPI — ДРР в коридоре 15–25%. Пики сентябрь/октябрь (школа) и январь (зима) — усиливаем категорийный Поиск и товарную галерею, плюс интересы и ретаргетинг РСЯ; летом (июнь–июль) ниже базы — первым режем автотаргетинг РСЯ, бренд-Поиск и ретаргет не трогаем. Если после запуска средний чек или CR в кабинете расходятся с планом — правим параметры или бенчи на «Инструментах», а не пересчитываем вручную строки года.

Sheet Инструменты
A1: Инструменты: 6 кампаний ЕПК и бенчмарки воронки
A2: Поиск и РСЯ в одной кампании не смешиваю: иначе не прочитаем аукцион и CR. 32% на категорийный поиск — основной спрос родителей. Бренд дешевле клика, его задача — забрать свой трафик, не растить охват. Доля × бюджет из листа «Параметры плана» ('Параметры плана'!$C$6) — опорный месяц (вес 1,0); на сетке года к расходу кампании умножаются сезонные веса. CTR/CPC/CR — жёлтые входы.
A4: # | B4: Кампания | C4: Тип кампании | D4: Тип площадки | E4: Доп. инструменты | F4: Тип объявлений | G4: Стратегия | H4: Доля бюджета | I4: Бюджет/мес, ₽ | J4: CTR | K4: CPC, ₽ | L4: CR в покупку | M4: Клики/мес | N4: Покупки/мес
A5: 1 | B5: ECCO Kids · бренд · Поиск | C5: ЕПК | D5: Поиск | E5: ключи бренд / бренд+товар | F5: текстово-графические | G5: Максимум конверсий | H5: 0.18 | I5: =ROUND('Параметры плана'!$C$6*H5,0) | J5: 0.1 | K5: 28 | L5: 0.065 | M5: =IF(K5=0,0,ROUND(I5/K5,0)) | N5: =ROUND(M5*L5,0)
A6: 2 | B6: ECCO Kids · категория boys · Поиск | C6: ЕПК | D6: Поиск | E6: ключи категория kids/boys/кроссовки | F6: текстово-графические | G6: Максимум конверсий | H6: 0.32 | I6: =ROUND('Параметры плана'!$C$6*H6,0) | J6: 0.045 | K6: 48 | L6: 0.038 | M6: =IF(K6=0,0,ROUND(I6/K6,0)) | N6: =ROUND(M6*L6,0)
A7: 3 | B7: ECCO Kids · товарная галерея · Поиск | C7: ЕПК | D7: Поиск | E7: фид + товарные объявления | F7: товарные | G7: Максимум конверсий | H7: 0.15 | I7: =ROUND('Параметры плана'!$C$6*H7,0) | J7: 0.07 | K7: 44 | L7: 0.045 | M7: =IF(K7=0,0,ROUND(I7/K7,0)) | N7: =ROUND(M7*L7,0)
A8: 4 | B8: ECCO Kids · интересы и ретаргетинг · РСЯ | C8: ЕПК | D8: РСЯ | E8: интересы (kids/fashion/родители) + ретаргетинг визитов/корзины | F8: графические + текстово-графические | G8: Максимум конверсий | H8: 0.2 | I8: =ROUND('Параметры плана'!$C$6*H8,0) | J8: 0.008 | K8: 11 | L8: 0.025 | M8: =IF(K8=0,0,ROUND(I8/K8,0)) | N8: =ROUND(M8*L8,0)
A9: 5 | B9: ECCO Kids · автотаргетинг · РСЯ | C9: ЕПК | D9: РСЯ | E9: автотаргетинг | F9: графические + текстово-графические | G9: Максимум кликов | H9: 0.1 | I9: =ROUND('Параметры плана'!$C$6*H9,0) | J9: 0.008 | K9: 11 | L9: 0.015 | M9: =IF(K9=0,0,ROUND(I9/K9,0)) | N9: =ROUND(M9*L9,0)
A10: 6 | B10: ECCO Kids · защита бренда · РСЯ | C10: ЕПК | D10: РСЯ | E10: бренд в сетях | F10: графические + текстово-графические | G10: Максимум конверсий | H10: 0.05 | I10: =ROUND('Параметры плана'!$C$6*H10,0) | J10: 0.008 | K10: 11 | L10: 0.025 | M10: =IF(K10=0,0,ROUND(I10/K10,0)) | N10: =ROUND(M10*L10,0)
B11: Итого / месяц | H11: =SUM(H5:H10) | I11: =SUM(I5:I10) | M11: =SUM(M5:M10) | N11: =SUM(N5:N10)
A13: Проверка месяца (формулы)
A14: Выручка / мес | C14: =ROUND(N11*'Параметры плана'!$C$7,0) | D14: ₽
A15: ДРР / мес | C15: =IF(C14=0,0,I11/C14) | D15: %
A16: CPA / мес | C16: =IF(N11=0,0,I11/N11) | D16: ₽
A17: Контроль долей | C17: =IF(ABS(H11-1)<0.0001,"OK: 100%","Ошибка: сумма долей ≠ 100%")
A19: Обоснование сплита и расчёта
A20: Кампания | B20: Места показа | C20: Доля / расход | D20: Почему этот тип кампании и условие показа | E20: Почему такая доля бюджета | F20: Экономика месяца
A21: =B5 | B21: Поиск | C21: =TEXT(H5,"0%")&" ("&TEXT(I5,"#,##0")&" ₽/мес)" | D21: Тип: ЕПК, места показа только Поиск, объявления текстово-графические, стратегия «Максимум конверсий», цель Метрики «Покупка на сайте». Условие показа — ключи бренд и бренд+товар. Почему тип: бренд в Поиске — самый дешёвый и предсказуемый спрос. Смешивать с РСЯ нельзя: другой аукцион и другой CR. | E21: Почему 18% (180 000 ₽/мес): этого достаточно, чтобы забрать свой спрос, но не раздувать бренд сверх частотности. Основной объём категории должен жить в небренде. | F21: Экономика (допущение, не кабинет): CTR 10,0%, CPC 28 ₽ → ~6 429 кликов; CR 6,5% → ~418 покупок; CPA ≈ 431 ₽; выручка ≈ 1,78 млн ₽; ДРР ≈ 10%. Это якорь канала: низкий ДРР компенсирует более дорогой категорийный поиск.
A22: =B6 | B22: Поиск | C22: =TEXT(H6,"0%")&" ("&TEXT(I6,"#,##0")&" ₽/мес)" | D22: Тип: ЕПК, Поиск, ТГО, «Максимум конверсий», ключи категория kids/boys/кроссовки/детская обувь — спрос родителей, не бренд. Почему тип: без категорийного Поиска нет объёма покупок в e-com обуви. Товарные объявления сюда не кладу: фид и семантика — разные рычаги оптимизации. | E22: Почему 32% (320 000 ₽) — крупнейшая доля: это основной небренд-спрос. Меньше 25% — недобор категории; больше 40% — ДРР канала вылетает из коридора, потому что CPC 48 ₽ и CR 3,8% тяжелее бренда. | F22: Экономика: CTR 4,5%, CPC 48 ₽ → ~6 667 кликов; CR 3,8% → ~253 покупки; CPA ≈ 1 265 ₽; ДРР строки ≈ 30%. Строка «дорогая» сознательно: её тянет бренд и РСЯ-ретаргет с ДРР ~10%.
A23: =B7 | B23: Поиск | C23: =TEXT(H7,"0%")&" ("&TEXT(I7,"#,##0")&" ₽/мес)" | D23: Тип: ЕПК, Поиск, товарные объявления (фид), «Максимум конверсий». Не путать с типом кампании: ЕПК — кампания, товарное — тип объявления. Почему тип: карточка товара на Поиске поднимает CTR vs текст (7% vs 4,5%) и закрывает SKU kids/boys без отдельной «медийки». | E23: Почему 15% (150 000 ₽): фид должен получить статистику на обучение стратегии, но не съесть семантику. 10% мало для фида, 25% дублирует категорийный поиск. | F23: Экономика: CTR 7,0%, CPC 44 ₽ → ~3 409 кликов; CR 4,5% → ~153 покупки; CPA ≈ 980 ₽; ДРР ≈ 23% — середина между брендом и категорией.
A24: =B8 | B24: РСЯ | C24: =TEXT(H8,"0%")&" ("&TEXT(I8,"#,##0")&" ₽/мес)" | D24: Тип: ЕПК, места показа только РСЯ, графика + ТГО, «Максимум конверсий». Условие показа: интересы (kids/fashion/родители) + ретаргетинг визитов и корзины. Почему тип: сети закрывают тех, кто не ввёл запрос, и дожимают визит/корзину. Поиск сюда не мешаю. | E24: Почему 20% (200 000 ₽): e-com kids без ретаргета теряет догрев. Больше 25% РСЯ-интересов размывает ДРР: CTR сети 0,8%, конверсия холоднее Поиска. | F24: Экономика: CPC 11 ₽ → ~18 182 клика; CR 2,5% → ~455 покупок; CPA ≈ 440 ₽; ДРР ≈ 10%. Дешёвый клик + тёплый ретаргет — второй якорь ДРР после бренда.
A25: =B9 | B25: РСЯ | C25: =TEXT(H9,"0%")&" ("&TEXT(I9,"#,##0")&" ₽/мес)" | D25: Тип: ЕПК, РСЯ, автотаргетинг, «Максимум кликов» (не «Максимум конверсий»: автотаргету сначала нужен объём кликов, CR ниже). Почему тип: автотаргетинг расширяет охват, но условие показа система берёт сама — CR падает до 1,5%. Держу отдельно, чтобы не портить статистику интересов/ретаргета. | E25: Почему 10% (100 000 ₽): тестовый объём. Резать первым, если факт ДРР > 25%. Не поднимать, пока CR не догонит интересы. | F25: Экономика: CPC 11 ₽ → ~9 091 клик; CR 1,5% → ~136 покупок; CPA ≈ 735 ₽; ДРР ≈ 17%. Плата за объём в сетях.
A26: =B10 | B26: РСЯ | C26: =TEXT(H10,"0%")&" ("&TEXT(I10,"#,##0")&" ₽/мес)" | D26: Тип: ЕПК, РСЯ, бренд в сетях, «Максимум конверсий», графика + ТГО. Почему тип: защита бренда в РСЯ, чтобы конкурент не перехватывал показ по бренду вне Поиска. Не смешивать с бренд-Поиском. | E26: Почему 5% (50 000 ₽): частотность бренда в сетях ограничена. 10%+ — переплата за те же аукционы. | F26: Экономика: CPC 11 ₽ → ~4 545 кликов; CR 2,5% → ~114 покупок; CPA ≈ 439 ₽; ДРР ≈ 10%.
A28: Комментарий к расчёту
A29: Главное в сплите — два якоря с низким ДРР: бренд в Поиске и ретаргет в РСЯ. Они перекрывают «тяжёлую» категорийную строку с CPC 48 ₽ — без этого микс не проходит коридор 15–25%. Категория 32% — не жадность, а единственный источник объёма небренда; резать её первой нельзя. Автотаргетинг держу отдельно и с «Максимум кликов»: это буфер на объём, его снимаем при первом признаке просадки CR, не трогая бренд и ретаргет. Таблица обоснования выше — логика долей; цифры месяца пересчитаются сами при смене жёлтых бенчей.

Sheet Медиаплан на год
A1: Медиаплан на год: 6 кампаний × 12 месяцев (все цифры — формулы)
A2: Сетка — 6 ЕПК × 12 месяцев; бюджет строки = база «Инструментов» × сезонный вес с «Параметры плана» ('Параметры плана'!$A$21:$B$32). ДРР года = сумма расхода / сумма выручки, не среднее ДРР строк. Крутим жёлтые CTR/CPC/CR на «Инструментах», не копируем итоги. Показы = клики / CTR; клики = бюджет / CPC; покупки = клики × CR; выручка = покупки × AOV.
A4: Месяц | B4: Кампания | C4: Тип площадки | D4: Доп. инструменты | E4: Стратегия | F4: Бюджет, ₽ | G4: CTR | H4: CPC, ₽ | I4: Показы | J4: Клики | K4: CR | L4: Покупки | M4: Выручка, ₽ | N4: ДРР
A5: Сен 2026 | B5: =Инструменты!B5 | C5: =Инструменты!D5 | D5: =Инструменты!E5 | E5: =Инструменты!G5 | F5: =ROUND(Инструменты!I5*VLOOKUP(A5,'Параметры плана'!$A$21:$B$32,2,FALSE),0) | G5: =Инструменты!J5 | H5: =Инструменты!K5 | I5: =IF(G5=0,0,ROUND(J5/G5,0)) | J5: =IF(H5=0,0,ROUND(F5/H5,0)) | K5: =Инструменты!L5 | L5: =ROUND(J5*K5,0) | M5: =ROUND(L5*'Параметры плана'!$C$7,0) | N5: =IF(M5=0,0,F5/M5)
A6: Сен 2026 | B6: =Инструменты!B6 | C6: =Инструменты!D6 | D6: =Инструменты!E6 | E6: =Инструменты!G6 | F6: =ROUND(Инструменты!I6*VLOOKUP(A6,'Параметры плана'!$A$21:$B$32,2,FALSE),0) | G6: =Инструменты!J6 | H6: =Инструменты!K6 | I6: =IF(G6=0,0,ROUND(J6/G6,0)) | J6: =IF(H6=0,0,ROUND(F6/H6,0)) | K6: =Инструменты!L6 | L6: =ROUND(J6*K6,0) | M6: =ROUND(L6*'Параметры плана'!$C$7,0) | N6: =IF(M6=0,0,F6/M6)
A7: Сен 2026 | B7: =Инструменты!B7 | C7: =Инструменты!D7 | D7: =Инструменты!E7 | E7: =Инструменты!G7 | F7: =ROUND(Инструменты!I7*VLOOKUP(A7,'Параметры плана'!$A$21:$B$32,2,FALSE),0) | G7: =Инструменты!J7 | H7: =Инструменты!K7 | I7: =IF(G7=0,0,ROUND(J7/G7,0)) | J7: =IF(H7=0,0,ROUND(F7/H7,0)) | K7: =Инструменты!L7 | L7: =ROUND(J7*K7,0) | M7: =ROUND(L7*'Параметры плана'!$C$7,0) | N7: =IF(M7=0,0,F7/M7)
A8: Сен 2026 | B8: =Инструменты!B8 | C8: =Инструменты!D8 | D8: =Инструменты!E8 | E8: =Инструменты!G8 | F8: =ROUND(Инструменты!I8*VLOOKUP(A8,'Параметры плана'!$A$21:$B$32,2,FALSE),0) | G8: =Инструменты!J8 | H8: =Инструменты!K8 | I8: =IF(G8=0,0,ROUND(J8/G8,0)) | J8: =IF(H8=0,0,ROUND(F8/H8,0)) | K8: =Инструменты!L8 | L8: =ROUND(J8*K8,0) | M8: =ROUND(L8*'Параметры плана'!$C$7,0) | N8: =IF(M8=0,0,F8/M8)
A9: Сен 2026 | B9: =Инструменты!B9 | C9: =Инструменты!D9 | D9: =Инструменты!E9 | E9: =Инструменты!G9 | F9: =ROUND(Инструменты!I9*VLOOKUP(A9,'Параметры плана'!$A$21:$B$32,2,FALSE),0) | G9: =Инструменты!J9 | H9: =Инструменты!K9 | I9: =IF(G9=0,0,ROUND(J9/G9,0)) | J9: =IF(H9=0,0,ROUND(F9/H9,0)) | K9: =Инструменты!L9 | L9: =ROUND(J9*K9,0) | M9: =ROUND(L9*'Параметры плана'!$C$7,0) | N9: =IF(M9=0,0,F9/M9)
A10: Сен 2026 | B10: =Инструменты!B10 | C10: =Инструменты!D10 | D10: =Инструменты!E10 | E10: =Инструменты!G10 | F10: =ROUND(Инструменты!I10*VLOOKUP(A10,'Параметры плана'!$A$21:$B$32,2,FALSE),0) | G10: =Инструменты!J10 | H10: =Инструменты!K10 | I10: =IF(G10=0,0,ROUND(J10/G10,0)) | J10: =IF(H10=0,0,ROUND(F10/H10,0)) | K10: =Инструменты!L10 | L10: =ROUND(J10*K10,0) | M10: =ROUND(L10*'Параметры плана'!$C$7,0) | N10: =IF(M10=0,0,F10/M10)
A11: Окт 2026 | B11: =Инструменты!B5 | C11: =Инструменты!D5 | D11: =Инструменты!E5 | E11: =Инструменты!G5 | F11: =ROUND(Инструменты!I5*VLOOKUP(A11,'Параметры плана'!$A$21:$B$32,2,FALSE),0) | G11: =Инструменты!J5 | H11: =Инструменты!K5 | I11: =IF(G11=0,0,ROUND(J11/G11,0)) | J11: =IF(H11=0,0,ROUND(F11/H11,0)) | K11: =Инструменты!L5 | L11: =ROUND(J11*K11,0) | M11: =ROUND(L11*'Параметры плана'!$C$7,0) | N11: =IF(M11=0,0,F11/M11)
A12: Окт 2026 | B12: =Инструменты!B6 | C12: =Инструменты!D6 | D12: =Инструменты!E6 | E12: =Инструменты!G6 | F12: =ROUND(Инструменты!I6*VLOOKUP(A12,'Параметры плана'!$A$21:$B$32,2,FALSE),0) | G12: =Инструменты!J6 | H12: =Инструменты!K6 | I12: =IF(G12=0,0,ROUND(J12/G12,0)) | J12: =IF(H12=0,0,ROUND(F12/H12,0)) | K12: =Инструменты!L6 | L12: =ROUND(J12*K12,0) | M12: =ROUND(L12*'Параметры плана'!$C$7,0) | N12: =IF(M12=0,0,F12/M12)
A13: Окт 2026 | B13: =Инструменты!B7 | C13: =Инструменты!D7 | D13: =Инструменты!E7 | E13: =Инструменты!G7 | F13: =ROUND(Инструменты!I7*VLOOKUP(A13,'Параметры плана'!$A$21:$B$32,2,FALSE),0) | G13: =Инструменты!J7 | H13: =Инструменты!K7 | I13: =IF(G13=0,0,ROUND(J13/G13,0)) | J13: =IF(H13=0,0,ROUND(F13/H13,0)) | K13: =Инструменты!L7 | L13: =ROUND(J13*K13,0) | M13: =ROUND(L13*'Параметры плана'!$C$7,0) | N13: =IF(M13=0,0,F13/M13)
A14: Окт 2026 | B14: =Инструменты!B8 | C14: =Инструменты!D8 | D14: =Инструменты!E8 | E14: =Инструменты!G8 | F14: =ROUND(Инструменты!I8*VLOOKUP(A14,'Параметры плана'!$A$21:$B$32,2,FALSE),0) | G14: =Инструменты!J8 | H14: =Инструменты!K8 | I14: =IF(G14=0,0,ROUND(J14/G14,0)) | J14: =IF(H14=0,0,ROUND(F14/H14,0)) | K14: =Инструменты!L8 | L14: =ROUND(J14*K14,0) | M14: =ROUND(L14*'Параметры плана'!$C$7,0) | N14: =IF(M14=0,0,F14/M14)
A15: Окт 2026 | B15: =Инструменты!B9 | C15: =Инструменты!D9 | D15: =Инструменты!E9 | E15: =Инструменты!G9 | F15: =ROUND(Инструменты!I9*VLOOKUP(A15,'Параметры плана'!$A$21:$B$32,2,FALSE),0) | G15: =Инструменты!J9 | H15: =Инструменты!K9 | I15: =IF(G15=0,0,ROUND(J15/G15,0)) | J15: =IF(H15=0,0,ROUND(F15/H15,0)) | K15: =Инструменты!L9 | L15: =ROUND(J15*K15,0) | M15: =ROUND(L15*'Параметры плана'!$C$7,0) | N15: =IF(M15=0,0,F15/M15)
A16: Окт 2026 | B16: =Инструменты!B10 | C16: =Инструменты!D10 | D16: =Инструменты!E10 | E16: =Инструменты!G10 | F16: =ROUND(Инструменты!I10*VLOOKUP(A16,'Параметры плана'!$A$21:$B$32,2,FALSE),0) | G16: =Инструменты!J10 | H16: =Инструменты!K10 | I16: =IF(G16=0,0,ROUND(J16/G16,0)) | J16: =IF(H16=0,0,ROUND(F16/H16,0)) | K16: =Инструменты!L10 | L16: =ROUND(J16*K16,0) | M16: =ROUND(L16*'Параметры плана'!$C$7,0) | N16: =IF(M16=0,0,F16/M16)
A17: Ноя 2026 | B17: =Инструменты!B5 | C17: =Инструменты!D5 | D17: =Инструменты!E5 | E17: =Инструменты!G5 | F17: =ROUND(Инструменты!I5*VLOOKUP(A17,'Параметры плана'!$A$21:$B$32,2,FALSE),0) | G17: =Инструменты!J5 | H17: =Инструменты!K5 | I17: =IF(G17=0,0,ROUND(J17/G17,0)) | J17: =IF(H17=0,0,ROUND(F17/H17,0)) | K17: =Инструменты!L5 | L17: =ROUND(J17*K17,0) | M17: =ROUND(L17*'Параметры плана'!$C$7,0) | N17: =IF(M17=0,0,F17/M17)
A18: Ноя 2026 | B18: =Инструменты!B6 | C18: =Инструменты!D6 | D18: =Инструменты!E6 | E18: =Инструменты!G6 | F18: =ROUND(Инструменты!I6*VLOOKUP(A18,'Параметры плана'!$A$21:$B$32,2,FALSE),0) | G18: =Инструменты!J6 | H18: =Инструменты!K6 | I18: =IF(G18=0,0,ROUND(J18/G18,0)) | J18: =IF(H18=0,0,ROUND(F18/H18,0)) | K18: =Инструменты!L6 | L18: =ROUND(J18*K18,0) | M18: =ROUND(L18*'Параметры плана'!$C$7,0) | N18: =IF(M18=0,0,F18/M18)
A19: Ноя 2026 | B19: =Инструменты!B7 | C19: =Инструменты!D7 | D19: =Инструменты!E7 | E19: =Инструменты!G7 | F19: =ROUND(Инструменты!I7*VLOOKUP(A19,'Параметры плана'!$A$21:$B$32,2,FALSE),0) | G19: =Инструменты!J7 | H19: =Инструменты!K7 | I19: =IF(G19=0,0,ROUND(J19/G19,0)) | J19: =IF(H19=0,0,ROUND(F19/H19,0)) | K19: =Инструменты!L7 | L19: =ROUND(J19*K19,0) | M19: =ROUND(L19*'Параметры плана'!$C$7,0) | N19: =IF(M19=0,0,F19/M19)
A20: Ноя 2026 | B20: =Инструменты!B8 | C20: =Инструменты!D8 | D20: =Инструменты!E8 | E20: =Инструменты!G8 | F20: =ROUND(Инструменты!I8*VLOOKUP(A20,'Параметры плана'!$A$21:$B$32,2,FALSE),0) | G20: =Инструменты!J8 | H20: =Инструменты!K8 | I20: =IF(G20=0,0,ROUND(J20/G20,0)) | J20: =IF(H20=0,0,ROUND(F20/H20,0)) | K20: =Инструменты!L8 | L20: =ROUND(J20*K20,0) | M20: =ROUND(L20*'Параметры плана'!$C$7,0) | N20: =IF(M20=0,0,F20/M20)
A21: Ноя 2026 | B21: =Инструменты!B9 | C21: =Инструменты!D9 | D21: =Инструменты!E9 | E21: =Инструменты!G9 | F21: =ROUND(Инструменты!I9*VLOOKUP(A21,'Параметры плана'!$A$21:$B$32,2,FALSE),0) | G21: =Инструменты!J9 | H21: =Инструменты!K9 | I21: =IF(G21=0,0,ROUND(J21/G21,0)) | J21: =IF(H21=0,0,ROUND(F21/H21,0)) | K21: =Инструменты!L9 | L21: =ROUND(J21*K21,0) | M21: =ROUND(L21*'Параметры плана'!$C$7,0) | N21: =IF(M21=0,0,F21/M21)
A22: Ноя 2026 | B22: =Инструменты!B10 | C22: =Инструменты!D10 | D22: =Инструменты!E10 | E22: =Инструменты!G10 | F22: =ROUND(Инструменты!I10*VLOOKUP(A22,'Параметры плана'!$A$21:$B$32,2,FALSE),0) | G22: =Инструменты!J10 | H22: =Инструменты!K10 | I22: =IF(G22=0,0,ROUND(J22/G22,0)) | J22: =IF(H22=0,0,ROUND(F22/H22,0)) | K22: =Инструменты!L10 | L22: =ROUND(J22*K22,0) | M22: =ROUND(L22*'Параметры плана'!$C$7,0) | N22: =IF(M22=0,0,F22/M22)
A23: Дек 2026 | B23: =Инструменты!B5 | C23: =Инструменты!D5 | D23: =Инструменты!E5 | E23: =Инструменты!G5 | F23: =ROUND(Инструменты!I5*VLOOKUP(A23,'Параметры плана'!$A$21:$B$32,2,FALSE),0) | G23: =Инструменты!J5 | H23: =Инструменты!K5 | I23: =IF(G23=0,0,ROUND(J23/G23,0)) | J23: =IF(H23=0,0,ROUND(F23/H23,0)) | K23: =Инструменты!L5 | L23: =ROUND(J23*K23,0) | M23: =ROUND(L23*'Параметры плана'!$C$7,0) | N23: =IF(M23=0,0,F23/M23)
A24: Дек 2026 | B24: =Инструменты!B6 | C24: =Инструменты!D6 | D24: =Инструменты!E6 | E24: =Инструменты!G6 | F24: =ROUND(Инструменты!I6*VLOOKUP(A24,'Параметры плана'!$A$21:$B$32,2,FALSE),0) | G24: =Инструменты!J6 | H24: =Инструменты!K6 | I24: =IF(G24=0,0,ROUND(J24/G24,0)) | J24: =IF(H24=0,0,ROUND(F24/H24,0)) | K24: =Инструменты!L6 | L24: =ROUND(J24*K24,0) | M24: =ROUND(L24*'Параметры плана'!$C$7,0) | N24: =IF(M24=0,0,F24/M24)
A25: Дек 2026 | B25: =Инструменты!B7 | C25: =Инструменты!D7 | D25: =Инструменты!E7 | E25: =Инструменты!G7 | F25: =ROUND(Инструменты!I7*VLOOKUP(A25,'Параметры плана'!$A$21:$B$32,2,FALSE),0) | G25: =Инструменты!J7 | H25: =Инструменты!K7 | I25: =IF(G25=0,0,ROUND(J25/G25,0)) | J25: =IF(H25=0,0,ROUND(F25/H25,0)) | K25: =Инструменты!L7 | L25: =ROUND(J25*K25,0) | M25: =ROUND(L25*'Параметры плана'!$C$7,0) | N25: =IF(M25=0,0,F25/M25)
A26: Дек 2026 | B26: =Инструменты!B8 | C26: =Инструменты!D8 | D26: =Инструменты!E8 | E26: =Инструменты!G8 | F26: =ROUND(Инструменты!I8*VLOOKUP(A26,'Параметры плана'!$A$21:$B$32,2,FALSE),0) | G26: =Инструменты!J8 | H26: =Инструменты!K8 | I26: =IF(G26=0,0,ROUND(J26/G26,0)) | J26: =IF(H26=0,0,ROUND(F26/H26,0)) | K26: =Инструменты!L8 | L26: =ROUND(J26*K26,0) | M26: =ROUND(L26*'Параметры плана'!$C$7,0) | N26: =IF(M26=0,0,F26/M26)
A27: Дек 2026 | B27: =Инструменты!B9 | C27: =Инструменты!D9 | D27: =Инструменты!E9 | E27: =Инструменты!G9 | F27: =ROUND(Инструменты!I9*VLOOKUP(A27,'Параметры плана'!$A$21:$B$32,2,FALSE),0) | G27: =Инструменты!J9 | H27: =Инструменты!K9 | I27: =IF(G27=0,0,ROUND(J27/G27,0)) | J27: =IF(H27=0,0,ROUND(F27/H27,0)) | K27: =Инструменты!L9 | L27: =ROUND(J27*K27,0) | M27: =ROUND(L27*'Параметры плана'!$C$7,0) | N27: =IF(M27=0,0,F27/M27)
A28: Дек 2026 | B28: =Инструменты!B10 | C28: =Инструменты!D10 | D28: =Инструменты!E10 | E28: =Инструменты!G10 | F28: =ROUND(Инструменты!I10*VLOOKUP(A28,'Параметры плана'!$A$21:$B$32,2,FALSE),0) | G28: =Инструменты!J10 | H28: =Инструменты!K10 | I28: =IF(G28=0,0,ROUND(J28/G28,0)) | J28: =IF(H28=0,0,ROUND(F28/H28,0)) | K28: =Инструменты!L10 | L28: =ROUND(J28*K28,0) | M28: =ROUND(L28*'Параметры плана'!$C$7,0) | N28: =IF(M28=0,0,F28/M28)
A29: Янв 2027 | B29: =Инструменты!B5 | C29: =Инструменты!D5 | D29: =Инструменты!E5 | E29: =Инструменты!G5 | F29: =ROUND(Инструменты!I5*VLOOKUP(A29,'Параметры плана'!$A$21:$B$32,2,FALSE),0) | G29: =Инструменты!J5 | H29: =Инструменты!K5 | I29: =IF(G29=0,0,ROUND(J29/G29,0)) | J29: =IF(H29=0,0,ROUND(F29/H29,0)) | K29: =Инструменты!L5 | L29: =ROUND(J29*K29,0) | M29: =ROUND(L29*'Параметры плана'!$C$7,0) | N29: =IF(M29=0,0,F29/M29)
A30: Янв 2027 | B30: =Инструменты!B6 | C30: =Инструменты!D6 | D30: =Инструменты!E6 | E30: =Инструменты!G6 | F30: =ROUND(Инструменты!I6*VLOOKUP(A30,'Параметры плана'!$A$21:$B$32,2,FALSE),0) | G30: =Инструменты!J6 | H30: =Инструменты!K6 | I30: =IF(G30=0,0,ROUND(J30/G30,0)) | J30: =IF(H30=0,0,ROUND(F30/H30,0)) | K30: =Инструменты!L6 | L30: =ROUND(J30*K30,0) | M30: =ROUND(L30*'Параметры плана'!$C$7,0) | N30: =IF(M30=0,0,F30/M30)
A31: Янв 2027 | B31: =Инструменты!B7 | C31: =Инструменты!D7 | D31: =Инструменты!E7 | E31: =Инструменты!G7 | F31: =ROUND(Инструменты!I7*VLOOKUP(A31,'Параметры плана'!$A$21:$B$32,2,FALSE),0) | G31: =Инструменты!J7 | H31: =Инструменты!K7 | I31: =IF(G31=0,0,ROUND(J31/G31,0)) | J31: =IF(H31=0,0,ROUND(F31/H31,0)) | K31: =Инструменты!L7 | L31: =ROUND(J31*K31,0) | M31: =ROUND(L31*'Параметры плана'!$C$7,0) | N31: =IF(M31=0,0,F31/M31)
A32: Янв 2027 | B32: =Инструменты!B8 | C32: =Инструменты!D8 | D32: =Инструменты!E8 | E32: =Инструменты!G8 | F32: =ROUND(Инструменты!I8*VLOOKUP(A32,'Параметры плана'!$A$21:$B$32,2,FALSE),0) | G32: =Инструменты!J8 | H32: =Инструменты!K8 | I32: =IF(G32=0,0,ROUND(J32/G32,0)) | J32: =IF(H32=0,0,ROUND(F32/H32,0)) | K32: =Инструменты!L8 | L32: =ROUND(J32*K32,0) | M32: =ROUND(L32*'Параметры плана'!$C$7,0) | N32: =IF(M32=0,0,F32/M32)
A33: Янв 2027 | B33: =Инструменты!B9 | C33: =Инструменты!D9 | D33: =Инструменты!E9 | E33: =Инструменты!G9 | F33: =ROUND(Инструменты!I9*VLOOKUP(A33,'Параметры плана'!$A$21:$B$32,2,FALSE),0) | G33: =Инструменты!J9 | H33: =Инструменты!K9 | I33: =IF(G33=0,0,ROUND(J33/G33,0)) | J33: =IF(H33=0,0,ROUND(F33/H33,0)) | K33: =Инструменты!L9 | L33: =ROUND(J33*K33,0) | M33: =ROUND(L33*'Параметры плана'!$C$7,0) | N33: =IF(M33=0,0,F33/M33)
A34: Янв 2027 | B34: =Инструменты!B10 | C34: =Инструменты!D10 | D34: =Инструменты!E10 | E34: =Инструменты!G10 | F34: =ROUND(Инструменты!I10*VLOOKUP(A34,'Параметры плана'!$A$21:$B$32,2,FALSE),0) | G34: =Инструменты!J10 | H34: =Инструменты!K10 | I34: =IF(G34=0,0,ROUND(J34/G34,0)) | J34: =IF(H34=0,0,ROUND(F34/H34,0)) | K34: =Инструменты!L10 | L34: =ROUND(J34*K34,0) | M34: =ROUND(L34*'Параметры плана'!$C$7,0) | N34: =IF(M34=0,0,F34/M34)
A35: Фев 2027 | B35: =Инструменты!B5 | C35: =Инструменты!D5 | D35: =Инструменты!E5 | E35: =Инструменты!G5 | F35: =ROUND(Инструменты!I5*VLOOKUP(A35,'Параметры плана'!$A$21:$B$32,2,FALSE),0) | G35: =Инструменты!J5 | H35: =Инструменты!K5 | I35: =IF(G35=0,0,ROUND(J35/G35,0)) | J35: =IF(H35=0,0,ROUND(F35/H35,0)) | K35: =Инструменты!L5 | L35: =ROUND(J35*K35,0) | M35: =ROUND(L35*'Параметры плана'!$C$7,0) | N35: =IF(M35=0,0,F35/M35)
A36: Фев 2027 | B36: =Инструменты!B6 | C36: =Инструменты!D6 | D36: =Инструменты!E6 | E36: =Инструменты!G6 | F36: =ROUND(Инструменты!I6*VLOOKUP(A36,'Параметры плана'!$A$21:$B$32,2,FALSE),0) | G36: =Инструменты!J6 | H36: =Инструменты!K6 | I36: =IF(G36=0,0,ROUND(J36/G36,0)) | J36: =IF(H36=0,0,ROUND(F36/H36,0)) | K36: =Инструменты!L6 | L36: =ROUND(J36*K36,0) | M36: =ROUND(L36*'Параметры плана'!$C$7,0) | N36: =IF(M36=0,0,F36/M36)
A37: Фев 2027 | B37: =Инструменты!B7 | C37: =Инструменты!D7 | D37: =Инструменты!E7 | E37: =Инструменты!G7 | F37: =ROUND(Инструменты!I7*VLOOKUP(A37,'Параметры плана'!$A$21:$B$32,2,FALSE),0) | G37: =Инструменты!J7 | H37: =Инструменты!K7 | I37: =IF(G37=0,0,ROUND(J37/G37,0)) | J37: =IF(H37=0,0,ROUND(F37/H37,0)) | K37: =Инструменты!L7 | L37: =ROUND(J37*K37,0) | M37: =ROUND(L37*'Параметры плана'!$C$7,0) | N37: =IF(M37=0,0,F37/M37)
A38: Фев 2027 | B38: =Инструменты!B8 | C38: =Инструменты!D8 | D38: =Инструменты!E8 | E38: =Инструменты!G8 | F38: =ROUND(Инструменты!I8*VLOOKUP(A38,'Параметры плана'!$A$21:$B$32,2,FALSE),0) | G38: =Инструменты!J8 | H38: =Инструменты!K8 | I38: =IF(G38=0,0,ROUND(J38/G38,0)) | J38: =IF(H38=0,0,ROUND(F38/H38,0)) | K38: =Инструменты!L8 | L38: =ROUND(J38*K38,0) | M38: =ROUND(L38*'Параметры плана'!$C$7,0) | N38: =IF(M38=0,0,F38/M38)
A39: Фев 2027 | B39: =Инструменты!B9 | C39: =Инструменты!D9 | D39: =Инструменты!E9 | E39: =Инструменты!G9 | F39: =ROUND(Инструменты!I9*VLOOKUP(A39,'Параметры плана'!$A$21:$B$32,2,FALSE),0) | G39: =Инструменты!J9 | H39: =Инструменты!K9 | I39: =IF(G39=0,0,ROUND(J39/G39,0)) | J39: =IF(H39=0,0,ROUND(F39/H39,0)) | K39: =Инструменты!L9 | L39: =ROUND(J39*K39,0) | M39: =ROUND(L39*'Параметры плана'!$C$7,0) | N39: =IF(M39=0,0,F39/M39)
A40: Фев 2027 | B40: =Инструменты!B10 | C40: =Инструменты!D10 | D40: =Инструменты!E10 | E40: =Инструменты!G10 | F40: =ROUND(Инструменты!I10*VLOOKUP(A40,'Параметры плана'!$A$21:$B$32,2,FALSE),0) | G40: =Инструменты!J10 | H40: =Инструменты!K10 | I40: =IF(G40=0,0,ROUND(J40/G40,0)) | J40: =IF(H40=0,0,ROUND(F40/H40,0)) | K40: =Инструменты!L10 | L40: =ROUND(J40*K40,0) | M40: =ROUND(L40*'Параметры плана'!$C$7,0) | N40: =IF(M40=0,0,F40/M40)
A41: Мар 2027 | B41: =Инструменты!B5 | C41: =Инструменты!D5 | D41: =Инструменты!E5 | E41: =Инструменты!G5 | F41: =ROUND(Инструменты!I5*VLOOKUP(A41,'Параметры плана'!$A$21:$B$32,2,FALSE),0) | G41: =Инструменты!J5 | H41: =Инструменты!K5 | I41: =IF(G41=0,0,ROUND(J41/G41,0)) | J41: =IF(H41=0,0,ROUND(F41/H41,0)) | K41: =Инструменты!L5 | L41: =ROUND(J41*K41,0) | M41: =ROUND(L41*'Параметры плана'!$C$7,0) | N41: =IF(M41=0,0,F41/M41)
A42: Мар 2027 | B42: =Инструменты!B6 | C42: =Инструменты!D6 | D42: =Инструменты!E6 | E42: =Инструменты!G6 | F42: =ROUND(Инструменты!I6*VLOOKUP(A42,'Параметры плана'!$A$21:$B$32,2,FALSE),0) | G42: =Инструменты!J6 | H42: =Инструменты!K6 | I42: =IF(G42=0,0,ROUND(J42/G42,0)) | J42: =IF(H42=0,0,ROUND(F42/H42,0)) | K42: =Инструменты!L6 | L42: =ROUND(J42*K42,0) | M42: =ROUND(L42*'Параметры плана'!$C$7,0) | N42: =IF(M42=0,0,F42/M42)
A43: Мар 2027 | B43: =Инструменты!B7 | C43: =Инструменты!D7 | D43: =Инструменты!E7 | E43: =Инструменты!G7 | F43: =ROUND(Инструменты!I7*VLOOKUP(A43,'Параметры плана'!$A$21:$B$32,2,FALSE),0) | G43: =Инструменты!J7 | H43: =Инструменты!K7 | I43: =IF(G43=0,0,ROUND(J43/G43,0)) | J43: =IF(H43=0,0,ROUND(F43/H43,0)) | K43: =Инструменты!L7 | L43: =ROUND(J43*K43,0) | M43: =ROUND(L43*'Параметры плана'!$C$7,0) | N43: =IF(M43=0,0,F43/M43)
A44: Мар 2027 | B44: =Инструменты!B8 | C44: =Инструменты!D8 | D44: =Инструменты!E8 | E44: =Инструменты!G8 | F44: =ROUND(Инструменты!I8*VLOOKUP(A44,'Параметры плана'!$A$21:$B$32,2,FALSE),0) | G44: =Инструменты!J8 | H44: =Инструменты!K8 | I44: =IF(G44=0,0,ROUND(J44/G44,0)) | J44: =IF(H44=0,0,ROUND(F44/H44,0)) | K44: =Инструменты!L8 | L44: =ROUND(J44*K44,0) | M44: =ROUND(L44*'Параметры плана'!$C$7,0) | N44: =IF(M44=0,0,F44/M44)
A45: Мар 2027 | B45: =Инструменты!B9 | C45: =Инструменты!D9 | D45: =Инструменты!E9 | E45: =Инструменты!G9 | F45: =ROUND(Инструменты!I9*VLOOKUP(A45,'Параметры плана'!$A$21:$B$32,2,FALSE),0) | G45: =Инструменты!J9 | H45: =Инструменты!K9 | I45: =IF(G45=0,0,ROUND(J45/G45,0)) | J45: =IF(H45=0,0,ROUND(F45/H45,0)) | K45: =Инструменты!L9 | L45: =ROUND(J45*K45,0) | M45: =ROUND(L45*'Параметры плана'!$C$7,0) | N45: =IF(M45=0,0,F45/M45)
A46: Мар 2027 | B46: =Инструменты!B10 | C46: =Инструменты!D10 | D46: =Инструменты!E10 | E46: =Инструменты!G10 | F46: =ROUND(Инструменты!I10*VLOOKUP(A46,'Параметры плана'!$A$21:$B$32,2,FALSE),0) | G46: =Инструменты!J10 | H46: =Инструменты!K10 | I46: =IF(G46=0,0,ROUND(J46/G46,0)) | J46: =IF(H46=0,0,ROUND(F46/H46,0)) | K46: =Инструменты!L10 | L46: =ROUND(J46*K46,0) | M46: =ROUND(L46*'Параметры плана'!$C$7,0) | N46: =IF(M46=0,0,F46/M46)
A47: Апр 2027 | B47: =Инструменты!B5 | C47: =Инструменты!D5 | D47: =Инструменты!E5 | E47: =Инструменты!G5 | F47: =ROUND(Инструменты!I5*VLOOKUP(A47,'Параметры плана'!$A$21:$B$32,2,FALSE),0) | G47: =Инструменты!J5 | H47: =Инструменты!K5 | I47: =IF(G47=0,0,ROUND(J47/G47,0)) | J47: =IF(H47=0,0,ROUND(F47/H47,0)) | K47: =Инструменты!L5 | L47: =ROUND(J47*K47,0) | M47: =ROUND(L47*'Параметры плана'!$C$7,0) | N47: =IF(M47=0,0,F47/M47)
A48: Апр 2027 | B48: =Инструменты!B6 | C48: =Инструменты!D6 | D48: =Инструменты!E6 | E48: =Инструменты!G6 | F48: =ROUND(Инструменты!I6*VLOOKUP(A48,'Параметры плана'!$A$21:$B$32,2,FALSE),0) | G48: =Инструменты!J6 | H48: =Инструменты!K6 | I48: =IF(G48=0,0,ROUND(J48/G48,0)) | J48: =IF(H48=0,0,ROUND(F48/H48,0)) | K48: =Инструменты!L6 | L48: =ROUND(J48*K48,0) | M48: =ROUND(L48*'Параметры плана'!$C$7,0) | N48: =IF(M48=0,0,F48/M48)
A49: Апр 2027 | B49: =Инструменты!B7 | C49: =Инструменты!D7 | D49: =Инструменты!E7 | E49: =Инструменты!G7 | F49: =ROUND(Инструменты!I7*VLOOKUP(A49,'Параметры плана'!$A$21:$B$32,2,FALSE),0) | G49: =Инструменты!J7 | H49: =Инструменты!K7 | I49: =IF(G49=0,0,ROUND(J49/G49,0)) | J49: =IF(H49=0,0,ROUND(F49/H49,0)) | K49: =Инструменты!L7 | L49: =ROUND(J49*K49,0) | M49: =ROUND(L49*'Параметры плана'!$C$7,0) | N49: =IF(M49=0,0,F49/M49)
A50: Апр 2027 | B50: =Инструменты!B8 | C50: =Инструменты!D8 | D50: =Инструменты!E8 | E50: =Инструменты!G8 | F50: =ROUND(Инструменты!I8*VLOOKUP(A50,'Параметры плана'!$A$21:$B$32,2,FALSE),0) | G50: =Инструменты!J8 | H50: =Инструменты!K8 | I50: =IF(G50=0,0,ROUND(J50/G50,0)) | J50: =IF(H50=0,0,ROUND(F50/H50,0)) | K50: =Инструменты!L8 | L50: =ROUND(J50*K50,0) | M50: =ROUND(L50*'Параметры плана'!$C$7,0) | N50: =IF(M50=0,0,F50/M50)
A51: Апр 2027 | B51: =Инструменты!B9 | C51: =Инструменты!D9 | D51: =Инструменты!E9 | E51: =Инструменты!G9 | F51: =ROUND(Инструменты!I9*VLOOKUP(A51,'Параметры плана'!$A$21:$B$32,2,FALSE),0) | G51: =Инструменты!J9 | H51: =Инструменты!K9 | I51: =IF(G51=0,0,ROUND(J51/G51,0)) | J51: =IF(H51=0,0,ROUND(F51/H51,0)) | K51: =Инструменты!L9 | L51: =ROUND(J51*K51,0) | M51: =ROUND(L51*'Параметры плана'!$C$7,0) | N51: =IF(M51=0,0,F51/M51)
A52: Апр 2027 | B52: =Инструменты!B10 | C52: =Инструменты!D10 | D52: =Инструменты!E10 | E52: =Инструменты!G10 | F52: =ROUND(Инструменты!I10*VLOOKUP(A52,'Параметры плана'!$A$21:$B$32,2,FALSE),0) | G52: =Инструменты!J10 | H52: =Инструменты!K10 | I52: =IF(G52=0,0,ROUND(J52/G52,0)) | J52: =IF(H52=0,0,ROUND(F52/H52,0)) | K52: =Инструменты!L10 | L52: =ROUND(J52*K52,0) | M52: =ROUND(L52*'Параметры плана'!$C$7,0) | N52: =IF(M52=0,0,F52/M52)
A53: Май 2027 | B53: =Инструменты!B5 | C53: =Инструменты!D5 | D53: =Инструменты!E5 | E53: =Инструменты!G5 | F53: =ROUND(Инструменты!I5*VLOOKUP(A53,'Параметры плана'!$A$21:$B$32,2,FALSE),0) | G53: =Инструменты!J5 | H53: =Инструменты!K5 | I53: =IF(G53=0,0,ROUND(J53/G53,0)) | J53: =IF(H53=0,0,ROUND(F53/H53,0)) | K53: =Инструменты!L5 | L53: =ROUND(J53*K53,0) | M53: =ROUND(L53*'Параметры плана'!$C$7,0) | N53: =IF(M53=0,0,F53/M53)
A54: Май 2027 | B54: =Инструменты!B6 | C54: =Инструменты!D6 | D54: =Инструменты!E6 | E54: =Инструменты!G6 | F54: =ROUND(Инструменты!I6*VLOOKUP(A54,'Параметры плана'!$A$21:$B$32,2,FALSE),0) | G54: =Инструменты!J6 | H54: =Инструменты!K6 | I54: =IF(G54=0,0,ROUND(J54/G54,0)) | J54: =IF(H54=0,0,ROUND(F54/H54,0)) | K54: =Инструменты!L6 | L54: =ROUND(J54*K54,0) | M54: =ROUND(L54*'Параметры плана'!$C$7,0) | N54: =IF(M54=0,0,F54/M54)
A55: Май 2027 | B55: =Инструменты!B7 | C55: =Инструменты!D7 | D55: =Инструменты!E7 | E55: =Инструменты!G7 | F55: =ROUND(Инструменты!I7*VLOOKUP(A55,'Параметры плана'!$A$21:$B$32,2,FALSE),0) | G55: =Инструменты!J7 | H55: =Инструменты!K7 | I55: =IF(G55=0,0,ROUND(J55/G55,0)) | J55: =IF(H55=0,0,ROUND(F55/H55,0)) | K55: =Инструменты!L7 | L55: =ROUND(J55*K55,0) | M55: =ROUND(L55*'Параметры плана'!$C$7,0) | N55: =IF(M55=0,0,F55/M55)
A56: Май 2027 | B56: =Инструменты!B8 | C56: =Инструменты!D8 | D56: =Инструменты!E8 | E56: =Инструменты!G8 | F56: =ROUND(Инструменты!I8*VLOOKUP(A56,'Параметры плана'!$A$21:$B$32,2,FALSE),0) | G56: =Инструменты!J8 | H56: =Инструменты!K8 | I56: =IF(G56=0,0,ROUND(J56/G56,0)) | J56: =IF(H56=0,0,ROUND(F56/H56,0)) | K56: =Инструменты!L8 | L56: =ROUND(J56*K56,0) | M56: =ROUND(L56*'Параметры плана'!$C$7,0) | N56: =IF(M56=0,0,F56/M56)
A57: Май 2027 | B57: =Инструменты!B9 | C57: =Инструменты!D9 | D57: =Инструменты!E9 | E57: =Инструменты!G9 | F57: =ROUND(Инструменты!I9*VLOOKUP(A57,'Параметры плана'!$A$21:$B$32,2,FALSE),0) | G57: =Инструменты!J9 | H57: =Инструменты!K9 | I57: =IF(G57=0,0,ROUND(J57/G57,0)) | J57: =IF(H57=0,0,ROUND(F57/H57,0)) | K57: =Инструменты!L9 | L57: =ROUND(J57*K57,0) | M57: =ROUND(L57*'Параметры плана'!$C$7,0) | N57: =IF(M57=0,0,F57/M57)
A58: Май 2027 | B58: =Инструменты!B10 | C58: =Инструменты!D10 | D58: =Инструменты!E10 | E58: =Инструменты!G10 | F58: =ROUND(Инструменты!I10*VLOOKUP(A58,'Параметры плана'!$A$21:$B$32,2,FALSE),0) | G58: =Инструменты!J10 | H58: =Инструменты!K10 | I58: =IF(G58=0,0,ROUND(J58/G58,0)) | J58: =IF(H58=0,0,ROUND(F58/H58,0)) | K58: =Инструменты!L10 | L58: =ROUND(J58*K58,0) | M58: =ROUND(L58*'Параметры плана'!$C$7,0) | N58: =IF(M58=0,0,F58/M58)
A59: Июн 2027 | B59: =Инструменты!B5 | C59: =Инструменты!D5 | D59: =Инструменты!E5 | E59: =Инструменты!G5 | F59: =ROUND(Инструменты!I5*VLOOKUP(A59,'Параметры плана'!$A$21:$B$32,2,FALSE),0) | G59: =Инструменты!J5 | H59: =Инструменты!K5 | I59: =IF(G59=0,0,ROUND(J59/G59,0)) | J59: =IF(H59=0,0,ROUND(F59/H59,0)) | K59: =Инструменты!L5 | L59: =ROUND(J59*K59,0) | M59: =ROUND(L59*'Параметры плана'!$C$7,0) | N59: =IF(M59=0,0,F59/M59)
A60: Июн 2027 | B60: =Инструменты!B6 | C60: =Инструменты!D6 | D60: =Инструменты!E6 | E60: =Инструменты!G6 | F60: =ROUND(Инструменты!I6*VLOOKUP(A60,'Параметры плана'!$A$21:$B$32,2,FALSE),0) | G60: =Инструменты!J6 | H60: =Инструменты!K6 | I60: =IF(G60=0,0,ROUND(J60/G60,0)) | J60: =IF(H60=0,0,ROUND(F60/H60,0)) | K60: =Инструменты!L6 | L60: =ROUND(J60*K60,0) | M60: =ROUND(L60*'Параметры плана'!$C$7,0) | N60: =IF(M60=0,0,F60/M60)
A61: Июн 2027 | B61: =Инструменты!B7 | C61: =Инструменты!D7 | D61: =Инструменты!E7 | E61: =Инструменты!G7 | F61: =ROUND(Инструменты!I7*VLOOKUP(A61,'Параметры плана'!$A$21:$B$32,2,FALSE),0) | G61: =Инструменты!J7 | H61: =Инструменты!K7 | I61: =IF(G61=0,0,ROUND(J61/G61,0)) | J61: =IF(H61=0,0,ROUND(F61/H61,0)) | K61: =Инструменты!L7 | L61: =ROUND(J61*K61,0) | M61: =ROUND(L61*'Параметры плана'!$C$7,0) | N61: =IF(M61=0,0,F61/M61)
A62: Июн 2027 | B62: =Инструменты!B8 | C62: =Инструменты!D8 | D62: =Инструменты!E8 | E62: =Инструменты!G8 | F62: =ROUND(Инструменты!I8*VLOOKUP(A62,'Параметры плана'!$A$21:$B$32,2,FALSE),0) | G62: =Инструменты!J8 | H62: =Инструменты!K8 | I62: =IF(G62=0,0,ROUND(J62/G62,0)) | J62: =IF(H62=0,0,ROUND(F62/H62,0)) | K62: =Инструменты!L8 | L62: =ROUND(J62*K62,0) | M62: =ROUND(L62*'Параметры плана'!$C$7,0) | N62: =IF(M62=0,0,F62/M62)
A63: Июн 2027 | B63: =Инструменты!B9 | C63: =Инструменты!D9 | D63: =Инструменты!E9 | E63: =Инструменты!G9 | F63: =ROUND(Инструменты!I9*VLOOKUP(A63,'Параметры плана'!$A$21:$B$32,2,FALSE),0) | G63: =Инструменты!J9 | H63: =Инструменты!K9 | I63: =IF(G63=0,0,ROUND(J63/G63,0)) | J63: =IF(H63=0,0,ROUND(F63/H63,0)) | K63: =Инструменты!L9 | L63: =ROUND(J63*K63,0) | M63: =ROUND(L63*'Параметры плана'!$C$7,0) | N63: =IF(M63=0,0,F63/M63)
A64: Июн 2027 | B64: =Инструменты!B10 | C64: =Инструменты!D10 | D64: =Инструменты!E10 | E64: =Инструменты!G10 | F64: =ROUND(Инструменты!I10*VLOOKUP(A64,'Параметры плана'!$A$21:$B$32,2,FALSE),0) | G64: =Инструменты!J10 | H64: =Инструменты!K10 | I64: =IF(G64=0,0,ROUND(J64/G64,0)) | J64: =IF(H64=0,0,ROUND(F64/H64,0)) | K64: =Инструменты!L10 | L64: =ROUND(J64*K64,0) | M64: =ROUND(L64*'Параметры плана'!$C$7,0) | N64: =IF(M64=0,0,F64/M64)
A65: Июл 2027 | B65: =Инструменты!B5 | C65: =Инструменты!D5 | D65: =Инструменты!E5 | E65: =Инструменты!G5 | F65: =ROUND(Инструменты!I5*VLOOKUP(A65,'Параметры плана'!$A$21:$B$32,2,FALSE),0) | G65: =Инструменты!J5 | H65: =Инструменты!K5 | I65: =IF(G65=0,0,ROUND(J65/G65,0)) | J65: =IF(H65=0,0,ROUND(F65/H65,0)) | K65: =Инструменты!L5 | L65: =ROUND(J65*K65,0) | M65: =ROUND(L65*'Параметры плана'!$C$7,0) | N65: =IF(M65=0,0,F65/M65)
A66: Июл 2027 | B66: =Инструменты!B6 | C66: =Инструменты!D6 | D66: =Инструменты!E6 | E66: =Инструменты!G6 | F66: =ROUND(Инструменты!I6*VLOOKUP(A66,'Параметры плана'!$A$21:$B$32,2,FALSE),0) | G66: =Инструменты!J6 | H66: =Инструменты!K6 | I66: =IF(G66=0,0,ROUND(J66/G66,0)) | J66: =IF(H66=0,0,ROUND(F66/H66,0)) | K66: =Инструменты!L6 | L66: =ROUND(J66*K66,0) | M66: =ROUND(L66*'Параметры плана'!$C$7,0) | N66: =IF(M66=0,0,F66/M66)
A67: Июл 2027 | B67: =Инструменты!B7 | C67: =Инструменты!D7 | D67: =Инструменты!E7 | E67: =Инструменты!G7 | F67: =ROUND(Инструменты!I7*VLOOKUP(A67,'Параметры плана'!$A$21:$B$32,2,FALSE),0) | G67: =Инструменты!J7 | H67: =Инструменты!K7 | I67: =IF(G67=0,0,ROUND(J67/G67,0)) | J67: =IF(H67=0,0,ROUND(F67/H67,0)) | K67: =Инструменты!L7 | L67: =ROUND(J67*K67,0) | M67: =ROUND(L67*'Параметры плана'!$C$7,0) | N67: =IF(M67=0,0,F67/M67)
A68: Июл 2027 | B68: =Инструменты!B8 | C68: =Инструменты!D8 | D68: =Инструменты!E8 | E68: =Инструменты!G8 | F68: =ROUND(Инструменты!I8*VLOOKUP(A68,'Параметры плана'!$A$21:$B$32,2,FALSE),0) | G68: =Инструменты!J8 | H68: =Инструменты!K8 | I68: =IF(G68=0,0,ROUND(J68/G68,0)) | J68: =IF(H68=0,0,ROUND(F68/H68,0)) | K68: =Инструменты!L8 | L68: =ROUND(J68*K68,0) | M68: =ROUND(L68*'Параметры плана'!$C$7,0) | N68: =IF(M68=0,0,F68/M68)
A69: Июл 2027 | B69: =Инструменты!B9 | C69: =Инструменты!D9 | D69: =Инструменты!E9 | E69: =Инструменты!G9 | F69: =ROUND(Инструменты!I9*VLOOKUP(A69,'Параметры плана'!$A$21:$B$32,2,FALSE),0) | G69: =Инструменты!J9 | H69: =Инструменты!K9 | I69: =IF(G69=0,0,ROUND(J69/G69,0)) | J69: =IF(H69=0,0,ROUND(F69/H69,0)) | K69: =Инструменты!L9 | L69: =ROUND(J69*K69,0) | M69: =ROUND(L69*'Параметры плана'!$C$7,0) | N69: =IF(M69=0,0,F69/M69)
A70: Июл 2027 | B70: =Инструменты!B10 | C70: =Инструменты!D10 | D70: =Инструменты!E10 | E70: =Инструменты!G10 | F70: =ROUND(Инструменты!I10*VLOOKUP(A70,'Параметры плана'!$A$21:$B$32,2,FALSE),0) | G70: =Инструменты!J10 | H70: =Инструменты!K10 | I70: =IF(G70=0,0,ROUND(J70/G70,0)) | J70: =IF(H70=0,0,ROUND(F70/H70,0)) | K70: =Инструменты!L10 | L70: =ROUND(J70*K70,0) | M70: =ROUND(L70*'Параметры плана'!$C$7,0) | N70: =IF(M70=0,0,F70/M70)
A71: Авг 2027 | B71: =Инструменты!B5 | C71: =Инструменты!D5 | D71: =Инструменты!E5 | E71: =Инструменты!G5 | F71: =ROUND(Инструменты!I5*VLOOKUP(A71,'Параметры плана'!$A$21:$B$32,2,FALSE),0) | G71: =Инструменты!J5 | H71: =Инструменты!K5 | I71: =IF(G71=0,0,ROUND(J71/G71,0)) | J71: =IF(H71=0,0,ROUND(F71/H71,0)) | K71: =Инструменты!L5 | L71: =ROUND(J71*K71,0) | M71: =ROUND(L71*'Параметры плана'!$C$7,0) | N71: =IF(M71=0,0,F71/M71)
A72: Авг 2027 | B72: =Инструменты!B6 | C72: =Инструменты!D6 | D72: =Инструменты!E6 | E72: =Инструменты!G6 | F72: =ROUND(Инструменты!I6*VLOOKUP(A72,'Параметры плана'!$A$21:$B$32,2,FALSE),0) | G72: =Инструменты!J6 | H72: =Инструменты!K6 | I72: =IF(G72=0,0,ROUND(J72/G72,0)) | J72: =IF(H72=0,0,ROUND(F72/H72,0)) | K72: =Инструменты!L6 | L72: =ROUND(J72*K72,0) | M72: =ROUND(L72*'Параметры плана'!$C$7,0) | N72: =IF(M72=0,0,F72/M72)
A73: Авг 2027 | B73: =Инструменты!B7 | C73: =Инструменты!D7 | D73: =Инструменты!E7 | E73: =Инструменты!G7 | F73: =ROUND(Инструменты!I7*VLOOKUP(A73,'Параметры плана'!$A$21:$B$32,2,FALSE),0) | G73: =Инструменты!J7 | H73: =Инструменты!K7 | I73: =IF(G73=0,0,ROUND(J73/G73,0)) | J73: =IF(H73=0,0,ROUND(F73/H73,0)) | K73: =Инструменты!L7 | L73: =ROUND(J73*K73,0) | M73: =ROUND(L73*'Параметры плана'!$C$7,0) | N73: =IF(M73=0,0,F73/M73)
A74: Авг 2027 | B74: =Инструменты!B8 | C74: =Инструменты!D8 | D74: =Инструменты!E8 | E74: =Инструменты!G8 | F74: =ROUND(Инструменты!I8*VLOOKUP(A74,'Параметры плана'!$A$21:$B$32,2,FALSE),0) | G74: =Инструменты!J8 | H74: =Инструменты!K8 | I74: =IF(G74=0,0,ROUND(J74/G74,0)) | J74: =IF(H74=0,0,ROUND(F74/H74,0)) | K74: =Инструменты!L8 | L74: =ROUND(J74*K74,0) | M74: =ROUND(L74*'Параметры плана'!$C$7,0) | N74: =IF(M74=0,0,F74/M74)
A75: Авг 2027 | B75: =Инструменты!B9 | C75: =Инструменты!D9 | D75: =Инструменты!E9 | E75: =Инструменты!G9 | F75: =ROUND(Инструменты!I9*VLOOKUP(A75,'Параметры плана'!$A$21:$B$32,2,FALSE),0) | G75: =Инструменты!J9 | H75: =Инструменты!K9 | I75: =IF(G75=0,0,ROUND(J75/G75,0)) | J75: =IF(H75=0,0,ROUND(F75/H75,0)) | K75: =Инструменты!L9 | L75: =ROUND(J75*K75,0) | M75: =ROUND(L75*'Параметры плана'!$C$7,0) | N75: =IF(M75=0,0,F75/M75)
A76: Авг 2027 | B76: =Инструменты!B10 | C76: =Инструменты!D10 | D76: =Инструменты!E10 | E76: =Инструменты!G10 | F76: =ROUND(Инструменты!I10*VLOOKUP(A76,'Параметры плана'!$A$21:$B$32,2,FALSE),0) | G76: =Инструменты!J10 | H76: =Инструменты!K10 | I76: =IF(G76=0,0,ROUND(J76/G76,0)) | J76: =IF(H76=0,0,ROUND(F76/H76,0)) | K76: =Инструменты!L10 | L76: =ROUND(J76*K76,0) | M76: =ROUND(L76*'Параметры плана'!$C$7,0) | N76: =IF(M76=0,0,F76/M76)
B77: Итого за год | F77: =SUM(F5:F76) | I77: =SUM(I5:I76) | J77: =SUM(J5:J76) | L77: =SUM(L5:L76) | M77: =SUM(M5:M76) | N77: =IF(M77=0,0,F77/M77)
A79: Комментарий к расчёту
A80: Сезонность заложена через веса на «Параметрах плана»: сентябрь/октябрь и январь выше базы, июнь–июль ниже — годовой потолок 12 млн сохраняется. В пиках смещаем объём в категорийный Поиск, товарную галерею и ретаргет РСЯ; в просадке летом первым режем автотаргетинг РСЯ, бренд-Поиск и ретаргет не трогаем — они держат ДРР. При проверке смотрите не на каждую строку, а на разрыв: категорийный Поиск будет «краснее» по ДРР, чем бренд и интересы — так и задумано. Если после запуска факт по категории стабильно хуже бенча, правим CR/CPC на «Инструментах», а не пересчитываем веса месяцев вслепую.

Sheet Сводка по месяцам
A1: Сводка по месяцам: SUMIF с листа «Медиаплан на год»
A2: SUMIF с листа «Медиаплан на год»: месяцы различаются по сезонным весам с «Параметры плана». ДРР месяца = сумма расхода / сумма выручки, не среднее ДРР кампаний.
A4: Месяц | B4: Расход, ₽ | C4: Показы | D4: Клики | E4: Покупки | F4: Выручка, ₽ | G4: ДРР | H4: CPA, ₽
A5: Сен 2026 | B5: =SUMIF('Медиаплан на год'!A:A,A5,'Медиаплан на год'!F:F) | C5: =SUMIF('Медиаплан на год'!A:A,A5,'Медиаплан на год'!I:I) | D5: =SUMIF('Медиаплан на год'!A:A,A5,'Медиаплан на год'!J:J) | E5: =SUMIF('Медиаплан на год'!A:A,A5,'Медиаплан на год'!L:L) | F5: =SUMIF('Медиаплан на год'!A:A,A5,'Медиаплан на год'!M:M) | G5: =IF(F5=0,0,B5/F5) | H5: =IF(E5=0,0,B5/E5)
A6: Окт 2026 | B6: =SUMIF('Медиаплан на год'!A:A,A6,'Медиаплан на год'!F:F) | C6: =SUMIF('Медиаплан на год'!A:A,A6,'Медиаплан на год'!I:I) | D6: =SUMIF('Медиаплан на год'!A:A,A6,'Медиаплан на год'!J:J) | E6: =SUMIF('Медиаплан на год'!A:A,A6,'Медиаплан на год'!L:L) | F6: =SUMIF('Медиаплан на год'!A:A,A6,'Медиаплан на год'!M:M) | G6: =IF(F6=0,0,B6/F6) | H6: =IF(E6=0,0,B6/E6)
A7: Ноя 2026 | B7: =SUMIF('Медиаплан на год'!A:A,A7,'Медиаплан на год'!F:F) | C7: =SUMIF('Медиаплан на год'!A:A,A7,'Медиаплан на год'!I:I) | D7: =SUMIF('Медиаплан на год'!A:A,A7,'Медиаплан на год'!J:J) | E7: =SUMIF('Медиаплан на год'!A:A,A7,'Медиаплан на год'!L:L) | F7: =SUMIF('Медиаплан на год'!A:A,A7,'Медиаплан на год'!M:M) | G7: =IF(F7=0,0,B7/F7) | H7: =IF(E7=0,0,B7/E7)
A8: Дек 2026 | B8: =SUMIF('Медиаплан на год'!A:A,A8,'Медиаплан на год'!F:F) | C8: =SUMIF('Медиаплан на год'!A:A,A8,'Медиаплан на год'!I:I) | D8: =SUMIF('Медиаплан на год'!A:A,A8,'Медиаплан на год'!J:J) | E8: =SUMIF('Медиаплан на год'!A:A,A8,'Медиаплан на год'!L:L) | F8: =SUMIF('Медиаплан на год'!A:A,A8,'Медиаплан на год'!M:M) | G8: =IF(F8=0,0,B8/F8) | H8: =IF(E8=0,0,B8/E8)
A9: Янв 2027 | B9: =SUMIF('Медиаплан на год'!A:A,A9,'Медиаплан на год'!F:F) | C9: =SUMIF('Медиаплан на год'!A:A,A9,'Медиаплан на год'!I:I) | D9: =SUMIF('Медиаплан на год'!A:A,A9,'Медиаплан на год'!J:J) | E9: =SUMIF('Медиаплан на год'!A:A,A9,'Медиаплан на год'!L:L) | F9: =SUMIF('Медиаплан на год'!A:A,A9,'Медиаплан на год'!M:M) | G9: =IF(F9=0,0,B9/F9) | H9: =IF(E9=0,0,B9/E9)
A10: Фев 2027 | B10: =SUMIF('Медиаплан на год'!A:A,A10,'Медиаплан на год'!F:F) | C10: =SUMIF('Медиаплан на год'!A:A,A10,'Медиаплан на год'!I:I) | D10: =SUMIF('Медиаплан на год'!A:A,A10,'Медиаплан на год'!J:J) | E10: =SUMIF('Медиаплан на год'!A:A,A10,'Медиаплан на год'!L:L) | F10: =SUMIF('Медиаплан на год'!A:A,A10,'Медиаплан на год'!M:M) | G10: =IF(F10=0,0,B10/F10) | H10: =IF(E10=0,0,B10/E10)
A11: Мар 2027 | B11: =SUMIF('Медиаплан на год'!A:A,A11,'Медиаплан на год'!F:F) | C11: =SUMIF('Медиаплан на год'!A:A,A11,'Медиаплан на год'!I:I) | D11: =SUMIF('Медиаплан на год'!A:A,A11,'Медиаплан на год'!J:J) | E11: =SUMIF('Медиаплан на год'!A:A,A11,'Медиаплан на год'!L:L) | F11: =SUMIF('Медиаплан на год'!A:A,A11,'Медиаплан на год'!M:M) | G11: =IF(F11=0,0,B11/F11) | H11: =IF(E11=0,0,B11/E11)
A12: Апр 2027 | B12: =SUMIF('Медиаплан на год'!A:A,A12,'Медиаплан на год'!F:F) | C12: =SUMIF('Медиаплан на год'!A:A,A12,'Медиаплан на год'!I:I) | D12: =SUMIF('Медиаплан на год'!A:A,A12,'Медиаплан на год'!J:J) | E12: =SUMIF('Медиаплан на год'!A:A,A12,'Медиаплан на год'!L:L) | F12: =SUMIF('Медиаплан на год'!A:A,A12,'Медиаплан на год'!M:M) | G12: =IF(F12=0,0,B12/F12) | H12: =IF(E12=0,0,B12/E12)
A13: Май 2027 | B13: =SUMIF('Медиаплан на год'!A:A,A13,'Медиаплан на год'!F:F) | C13: =SUMIF('Медиаплан на год'!A:A,A13,'Медиаплан на год'!I:I) | D13: =SUMIF('Медиаплан на год'!A:A,A13,'Медиаплан на год'!J:J) | E13: =SUMIF('Медиаплан на год'!A:A,A13,'Медиаплан на год'!L:L) | F13: =SUMIF('Медиаплан на год'!A:A,A13,'Медиаплан на год'!M:M) | G13: =IF(F13=0,0,B13/F13) | H13: =IF(E13=0,0,B13/E13)
A14: Июн 2027 | B14: =SUMIF('Медиаплан на год'!A:A,A14,'Медиаплан на год'!F:F) | C14: =SUMIF('Медиаплан на год'!A:A,A14,'Медиаплан на год'!I:I) | D14: =SUMIF('Медиаплан на год'!A:A,A14,'Медиаплан на год'!J:J) | E14: =SUMIF('Медиаплан на год'!A:A,A14,'Медиаплан на год'!L:L) | F14: =SUMIF('Медиаплан на год'!A:A,A14,'Медиаплан на год'!M:M) | G14: =IF(F14=0,0,B14/F14) | H14: =IF(E14=0,0,B14/E14)
A15: Июл 2027 | B15: =SUMIF('Медиаплан на год'!A:A,A15,'Медиаплан на год'!F:F) | C15: =SUMIF('Медиаплан на год'!A:A,A15,'Медиаплан на год'!I:I) | D15: =SUMIF('Медиаплан на год'!A:A,A15,'Медиаплан на год'!J:J) | E15: =SUMIF('Медиаплан на год'!A:A,A15,'Медиаплан на год'!L:L) | F15: =SUMIF('Медиаплан на год'!A:A,A15,'Медиаплан на год'!M:M) | G15: =IF(F15=0,0,B15/F15) | H15: =IF(E15=0,0,B15/E15)
A16: Авг 2027 | B16: =SUMIF('Медиаплан на год'!A:A,A16,'Медиаплан на год'!F:F) | C16: =SUMIF('Медиаплан на год'!A:A,A16,'Медиаплан на год'!I:I) | D16: =SUMIF('Медиаплан на год'!A:A,A16,'Медиаплан на год'!J:J) | E16: =SUMIF('Медиаплан на год'!A:A,A16,'Медиаплан на год'!L:L) | F16: =SUMIF('Медиаплан на год'!A:A,A16,'Медиаплан на год'!M:M) | G16: =IF(F16=0,0,B16/F16) | H16: =IF(E16=0,0,B16/E16)
A17: Итого год | B17: =SUM(B5:B16) | C17: =SUM(C5:C16) | D17: =SUM(D5:D16) | E17: =SUM(E5:E16) | F17: =SUM(F5:F16) | G17: =IF(F17=0,0,B17/F17) | H17: =IF(E17=0,0,B17/E17)
A19: Комментарий к расчёту
A20: Месяцы различаются: SUMIF тянет расход с сетки года, где к базовому бюджету кампании умножен сезонный вес с «Параметров плана». ДРР месяца считаю от сумм, не усредняю ДРР кампаний: иначе категория с ДРР ~30% «спрячется» за брендом. Сентябрь/октябрь и январь выше июня/июля — это школьный и зимний спрос; сумма 12 месяцев = 12 млн ₽, веса и логика сдвига описаны на «Параметрах плана».

Sheet Сводка за год
A1: Сводка за год: инструменты и KPI (SUMIF с «Медиаплан на год»)
A2: Коридор ДРР 15–25% — условие приёмки плана. Годовые KPI — сумма 12 сезонных месяцев с сетки года; доли и бенчи не меняются.
A4: Кампания | B4: Тип площадки | C4: Доп. инструменты | D4: Доля | E4: Расход год, ₽ | F4: Клики год | G4: Покупки год | H4: Выручка год, ₽ | I4: ДРР | J4: CPA, ₽ | K4: Вклад в покупки
A5: =Инструменты!B5 | B5: =Инструменты!D5 | C5: =Инструменты!E5 | D5: =Инструменты!H5 | E5: =SUMIF('Медиаплан на год'!B:B,A5,'Медиаплан на год'!F:F) | F5: =SUMIF('Медиаплан на год'!B:B,A5,'Медиаплан на год'!J:J) | G5: =SUMIF('Медиаплан на год'!B:B,A5,'Медиаплан на год'!L:L) | H5: =SUMIF('Медиаплан на год'!B:B,A5,'Медиаплан на год'!M:M) | I5: =IF(H5=0,0,E5/H5) | J5: =IF(G5=0,0,E5/G5) | K5: =IF(G$11=0,0,G5/G$11)
A6: =Инструменты!B6 | B6: =Инструменты!D6 | C6: =Инструменты!E6 | D6: =Инструменты!H6 | E6: =SUMIF('Медиаплан на год'!B:B,A6,'Медиаплан на год'!F:F) | F6: =SUMIF('Медиаплан на год'!B:B,A6,'Медиаплан на год'!J:J) | G6: =SUMIF('Медиаплан на год'!B:B,A6,'Медиаплан на год'!L:L) | H6: =SUMIF('Медиаплан на год'!B:B,A6,'Медиаплан на год'!M:M) | I6: =IF(H6=0,0,E6/H6) | J6: =IF(G6=0,0,E6/G6) | K6: =IF(G$11=0,0,G6/G$11)
A7: =Инструменты!B7 | B7: =Инструменты!D7 | C7: =Инструменты!E7 | D7: =Инструменты!H7 | E7: =SUMIF('Медиаплан на год'!B:B,A7,'Медиаплан на год'!F:F) | F7: =SUMIF('Медиаплан на год'!B:B,A7,'Медиаплан на год'!J:J) | G7: =SUMIF('Медиаплан на год'!B:B,A7,'Медиаплан на год'!L:L) | H7: =SUMIF('Медиаплан на год'!B:B,A7,'Медиаплан на год'!M:M) | I7: =IF(H7=0,0,E7/H7) | J7: =IF(G7=0,0,E7/G7) | K7: =IF(G$11=0,0,G7/G$11)
A8: =Инструменты!B8 | B8: =Инструменты!D8 | C8: =Инструменты!E8 | D8: =Инструменты!H8 | E8: =SUMIF('Медиаплан на год'!B:B,A8,'Медиаплан на год'!F:F) | F8: =SUMIF('Медиаплан на год'!B:B,A8,'Медиаплан на год'!J:J) | G8: =SUMIF('Медиаплан на год'!B:B,A8,'Медиаплан на год'!L:L) | H8: =SUMIF('Медиаплан на год'!B:B,A8,'Медиаплан на год'!M:M) | I8: =IF(H8=0,0,E8/H8) | J8: =IF(G8=0,0,E8/G8) | K8: =IF(G$11=0,0,G8/G$11)
A9: =Инструменты!B9 | B9: =Инструменты!D9 | C9: =Инструменты!E9 | D9: =Инструменты!H9 | E9: =SUMIF('Медиаплан на год'!B:B,A9,'Медиаплан на год'!F:F) | F9: =SUMIF('Медиаплан на год'!B:B,A9,'Медиаплан на год'!J:J) | G9: =SUMIF('Медиаплан на год'!B:B,A9,'Медиаплан на год'!L:L) | H9: =SUMIF('Медиаплан на год'!B:B,A9,'Медиаплан на год'!M:M) | I9: =IF(H9=0,0,E9/H9) | J9: =IF(G9=0,0,E9/G9) | K9: =IF(G$11=0,0,G9/G$11)
A10: =Инструменты!B10 | B10: =Инструменты!D10 | C10: =Инструменты!E10 | D10: =Инструменты!H10 | E10: =SUMIF('Медиаплан на год'!B:B,A10,'Медиаплан на год'!F:F) | F10: =SUMIF('Медиаплан на год'!B:B,A10,'Медиаплан на год'!J:J) | G10: =SUMIF('Медиаплан на год'!B:B,A10,'Медиаплан на год'!L:L) | H10: =SUMIF('Медиаплан на год'!B:B,A10,'Медиаплан на год'!M:M) | I10: =IF(H10=0,0,E10/H10) | J10: =IF(G10=0,0,E10/G10) | K10: =IF(G$11=0,0,G10/G$11)
A11: Итого год | D11: =SUM(D5:D10) | E11: =SUM(E5:E10) | F11: =SUM(F5:F10) | G11: =SUM(G5:G10) | H11: =SUM(H5:H10) | I11: =IF(H11=0,0,E11/H11) | J11: =IF(G11=0,0,E11/G11) | K11: =SUM(K5:K10)
A13: Сверка с сеткой года
A14: Расход (сводка) | B14: =E11 | C14: Расход (сетка) | D14: ='Медиаплан на год'!F77 | E14: Расхождение | F14: =B14-D14
A15: Выручка (сводка) | B15: =H11 | C15: Выручка (сетка) | D15: ='Медиаплан на год'!M77 | E15: Расхождение | F15: =B15-D15
A16: ДРР в коридоре 15–25% | B16: =IF(AND(I11>=0.15,I11<=0.25),"Да","Нет — проверьте бенчи")
A18: Комментарий к расчёту
A19: Приёмка плана — годовой ДРР в коридоре 15–25% (строка проверки). Годовые KPI — сумма 12 сезонных месяцев с «Медиаплана на год», не flat × 12. По вкладу в покупки лидирует не «самая дешёвая» кампания, а связка: категорийный Поиск даёт объём, ретаргет РСЯ — догрев, бренд — дешёвый захват своего спроса. Автотаргетинг с худшим CR не ломает год, потому что доля 10% и изолирована. После старта сверяем факт CR по каждому месту показа; бенчи в плане — рабочая гипотеза, не статистика кабинета ECCO.
